LICENSE
README.md
setup.py
tests/test_get_index_market_data.py
tests/test_requirements.py
tests/test_thrift_client.py
tests/test_ttdatasdk.py
ttdatasdk/__init__.py
ttdatasdk/api.py
ttdatasdk/client.py
ttdatasdk/exceptions.py
ttdatasdk/thrift_client.py
ttdatasdk/utils.py
ttdatasdk/version.py
ttdatasdk.egg-info/PKG-INFO
ttdatasdk.egg-info/SOURCES.txt
ttdatasdk.egg-info/dependency_links.txt
ttdatasdk.egg-info/not-zip-safe
ttdatasdk.egg-info/requires.txt
ttdatasdk.egg-info/top_level.txt
ttdatasdk/compat/__init__.py
ttdatasdk/compat/pickle_compat.py