Metadata-Version: 2.1
Name: ttdatasdk
Version: 0.0.3
Summary: Ticker Trading Factors data access, Backtest and Trading.
Home-page: https://www.tickertrading.com
Author: PinkQuant
Author-email: tickertrading@163.com
Maintainer: topbip
Maintainer-email: pinkquant@163.com
License: Apache License v2
Platform: all
Classifier: Programming Language :: Python
Classifier: Operating System :: Microsoft :: Windows
Classifier: Operating System :: Unix
Classifier: Development Status :: 3 - Alpha
Classifier: Intended Audience :: Developers
Classifier: Programming Language :: Python :: 3.8
License-File: LICENSE
